{
    "Log": {
        "Level": "debug"
    },
    "Http": {
        "SkipCertVerification": true
    },
    "ConnectionStrings": {
        "Mongo": "mongodb://sa:Famous901@192.168.188.166",
        "MySql": "root:Famous901@tcp(192.168.188.166:2883)/LogClients"
    },
    "Consul": {
        "Addr": "192.168.188.166:8500",
        "Token": "48359c9b-afc2-341f-9a61-ee37f3b361b6",
        "Service": {
            "Name": "logs",
            "Host": "192.168.188.166",
            "Port": 7159,
            "Check": {
                "Interval": "10s",
                "Timeout": "60s"
            }
        }
    },
    "DataAccess": {
        "ConnMaxLifetime": 180,
        "MaxOpenConns": 10,
        "MaxIdleConns": 10,
        "Provider": "mongodb"
    },
    "AsyncWriting": true,
    "Debug": true,
    "ListenAddr": ":7159"
}